{
  "posts": [
    {
      "id": "4",
      "title": "Understanding JavaScript Closures",
      "body": "Closures are a fundamental concept in JavaScript that allow functions to retain access to variables from their lexical scope even after the function has finished executing.",
      "author": {
        "id": 4,
        "name": "Dave Brown",
        "bio": "JavaScript expert and web performance advocate.",
        "email": "dave.brown@example.com",
        "profilePictureUrl": null,
        "createdAt": "2024-01-04T00:00:00Z"
      },
      "createdAt": "2024-09-04T16:45:00Z"
    },
    {
      "id": "5",
      "title": "Mastering CSS Grid",
      "body": "CSS Grid is a powerful layout system that provides a way to create complex grid-based designs with ease. It allows for more control over the layout of web pages.",
      "author": {
        "id": 5,
        "name": "Eve Davis",
        "bio": "CSS specialist and web design guru.",
        "email": "eve.davis@example.com",
        "profilePictureUrl": null,
        "createdAt": "2024-01-05T00:00:00Z"
      },
      "createdAt": "2024-09-05T09:00:00Z"
    },
    {
      "id": "1726150448538",
      "title": "New Post",
      "body": "test\\",
      "author": {
        "id": 1726150448538,
        "name": "Ismail",
        "createdAt": "2024-09-12T14:14:08.538Z",
        "profilePictureUrl": "assets/default-profile-picture-url.webp"
      },
      "createdAt": "2024-09-12T14:14:08.538Z"
    },
    {
      "id": "1726150529181",
      "title": "New Post",
      "body": "Hi",
      "author": {
        "id": 1726150529181,
        "name": "Ismail",
        "createdAt": "2024-09-12T14:15:29.181Z",
        "profilePictureUrl": "assets/default-profile-picture-url.webp"
      },
      "createdAt": "2024-09-12T14:15:29.181Z"
    }
  ]
}